[
  {
    "inputs": [],
    "stateMutability": "nonpayable",
    "type": "constructor"
  },
  {
    "inputs": [],
    "name": "ECDSAInvalidSignature",
    "type": "error"
  },
  {
    "inputs": [
      {
        "internalType": "uint256",
        "name": "length",
        "type": "uint256"
      }
    ],
    "name": "ECDSAInvalidSignatureLength",
    "type": "error"
  },
  {
    "inputs": [
      {
        "internalType": "bytes32",
        "name": "s",
        "type": "bytes32"
      }
    ],
    "name": "ECDSAInvalidSignatureS",
    "type": "error"
  },
  {
    "inputs": [
      {
        "internalType": "address",
        "name": "owner",
        "type": "address"
      }
    ],
    "name": "OwnableInvalidOwner",
    "type": "error"
  },
  {
    "inputs": [
      {
        "internalType": "address",
        "name": "account",
        "type": "address"
      }
    ],
    "name": "OwnableUnauthorizedAccount",
    "type": "error"
  },
  {
    "inputs": [],
    "name": "ReentrancyGuardReentrantCall",
    "type": "error"
  },
  {
    "anonymous": false,
    "inputs": [
      {
        "indexed": true,
        "internalType": "uint256",
        "name": "loanId",
        "type": "uint256"
      }
    ],
    "name": "LoanExpired",
    "type": "event"
  },
  {
    "anonymous": false,
    "inputs": [
      {
        "indexed": true,
        "internalType": "uint256",
        "name": "loanId",
        "type": "uint256"
      }
    ],
    "name": "LoanFunded",
    "type": "event"
  },
  {
    "anonymous": false,
    "inputs": [
      {
        "indexed": true,
        "internalType": "uint256",
        "name": "loanId",
        "type": "uint256"
      },
      {
        "indexed": false,
        "internalType": "uint256",
        "name": "amount",
        "type": "uint256"
      }
    ],
    "name": "LoanPartiallyRepaid",
    "type": "event"
  },
  {
    "anonymous": false,
    "inputs": [
      {
        "indexed": true,
        "internalType": "uint256",
        "name": "loanId",
        "type": "uint256"
      },
      {
        "indexed": true,
        "internalType": "address",
        "name": "lender",
        "type": "address"
      },
      {
        "indexed": true,
        "internalType": "address",
        "name": "borrower",
        "type": "address"
      },
      {
        "indexed": false,
        "internalType": "uint256",
        "name": "loanAmount",
        "type": "uint256"
      },
      {
        "indexed": false,
        "internalType": "uint256",
        "name": "repayAmount",
        "type": "uint256"
      },
      {
        "indexed": false,
        "internalType": "uint256",
        "name": "deadlineBlockNumber",
        "type": "uint256"
      }
    ],
    "name": "LoanRegistered",
    "type": "event"
  },
  {
    "anonymous": false,
    "inputs": [
      {
        "indexed": true,
        "internalType": "uint256",
        "name": "loanId",
        "type": "uint256"
      }
    ],
    "name": "LoanRepaid",
    "type": "event"
  },
  {
    "anonymous": false,
    "inputs": [
      {
        "indexed": true,
        "internalType": "address",
        "name": "previousOwner",
        "type": "address"
      },
      {
        "indexed": true,
        "internalType": "address",
        "name": "newOwner",
        "type": "address"
      }
    ],
    "name": "OwnershipTransferred",
    "type": "event"
  },
  {
    "inputs": [
      {
        "internalType": "uint256",
        "name": "loanId",
        "type": "uint256"
      }
    ],
    "name": "getLoanOrder",
    "outputs": [
      {
        "components": [
          {
            "components": [
              {
                "internalType": "address",
                "name": "from",
                "type": "address"
              },
              {
                "internalType": "address",
                "name": "to",
                "type": "address"
              },
              {
                "internalType": "address",
                "name": "withToken",
                "type": "address"
              }
            ],
            "internalType": "struct LoanFlow",
            "name": "fundFlow",
            "type": "tuple"
          },
          {
            "components": [
              {
                "internalType": "address",
                "name": "from",
                "type": "address"
              },
              {
                "internalType": "address",
                "name": "to",
                "type": "address"
              },
              {
                "internalType": "address",
                "name": "withToken",
                "type": "address"
              }
            ],
            "internalType": "struct LoanFlow",
            "name": "repayFlow",
            "type": "tuple"
          },
          {
            "components": [
              {
                "internalType": "uint256",
                "name": "loanAmount",
                "type": "uint256"
              },
              {
                "internalType": "uint256",
                "name": "interestRate",
                "type": "uint256"
              },
              {
                "internalType": "uint256",
                "name": "expectedRepaymentAmount",
                "type": "uint256"
              },
              {
                "internalType": "uint256",
                "name": "deadlineBlockNumber",
                "type": "uint256"
              }
            ],
            "internalType": "struct LoanTerms",
            "name": "terms",
            "type": "tuple"
          },
          {
            "internalType": "bytes",
            "name": "signatureOfLender",
            "type": "bytes"
          },
          {
            "internalType": "bytes",
            "name": "signatureOfBorrower",
            "type": "bytes"
          },
          {
            "internalType": "uint256",
            "name": "createdAtBlock",
            "type": "uint256"
          },
          {
            "internalType": "enum LoanStatus",
            "name": "status",
            "type": "uint8"
          },
          {
            "internalType": "uint256",
            "name": "repaidAmount",
            "type": "uint256"
          }
        ],
        "internalType": "struct LoanOrder",
        "name": "",
        "type": "tuple"
      }
    ],
    "stateMutability": "view",
    "type": "function"
  },
  {
    "inputs": [
      {
        "internalType": "uint256",
        "name": "",
        "type": "uint256"
      }
    ],
    "name": "loanOrders",
    "outputs": [
      {
        "components": [
          {
            "internalType": "address",
            "name": "from",
            "type": "address"
          },
          {
            "internalType": "address",
            "name": "to",
            "type": "address"
          },
          {
            "internalType": "address",
            "name": "withToken",
            "type": "address"
          }
        ],
        "internalType": "struct LoanFlow",
        "name": "fundFlow",
        "type": "tuple"
      },
      {
        "components": [
          {
            "internalType": "address",
            "name": "from",
            "type": "address"
          },
          {
            "internalType": "address",
            "name": "to",
            "type": "address"
          },
          {
            "internalType": "address",
            "name": "withToken",
            "type": "address"
          }
        ],
        "internalType": "struct LoanFlow",
        "name": "repayFlow",
        "type": "tuple"
      },
      {
        "components": [
          {
            "internalType": "uint256",
            "name": "loanAmount",
            "type": "uint256"
          },
          {
            "internalType": "uint256",
            "name": "interestRate",
            "type": "uint256"
          },
          {
            "internalType": "uint256",
            "name": "expectedRepaymentAmount",
            "type": "uint256"
          },
          {
            "internalType": "uint256",
            "name": "deadlineBlockNumber",
            "type": "uint256"
          }
        ],
        "internalType": "struct LoanTerms",
        "name": "terms",
        "type": "tuple"
      },
      {
        "internalType": "bytes",
        "name": "signatureOfLender",
        "type": "bytes"
      },
      {
        "internalType": "bytes",
        "name": "signatureOfBorrower",
        "type": "bytes"
      },
      {
        "internalType": "uint256",
        "name": "createdAtBlock",
        "type": "uint256"
      },
      {
        "internalType": "enum LoanStatus",
        "name": "status",
        "type": "uint8"
      },
      {
        "internalType": "uint256",
        "name": "repaidAmount",
        "type": "uint256"
      }
    ],
    "stateMutability": "view",
    "type": "function"
  },
  {
    "inputs": [
      {
        "internalType": "uint256",
        "name": "loanId",
        "type": "uint256"
      }
    ],
    "name": "markLoanAsExpired",
    "outputs": [],
    "stateMutability": "nonpayable",
    "type": "function"
  },
  {
    "inputs": [
      {
        "internalType": "uint256",
        "name": "loanId",
        "type": "uint256"
      }
    ],
    "name": "markLoanAsFunded",
    "outputs": [],
    "stateMutability": "nonpayable",
    "type": "function"
  },
  {
    "inputs": [],
    "name": "nextLoanId",
    "outputs": [
      {
        "internalType": "uint256",
        "name": "",
        "type": "uint256"
      }
    ],
    "stateMutability": "view",
    "type": "function"
  },
  {
    "inputs": [
      {
        "internalType": "uint256",
        "name": "loanId",
        "type": "uint256"
      },
      {
        "internalType": "uint256",
        "name": "amount",
        "type": "uint256"
      }
    ],
    "name": "noteLoanRepayment",
    "outputs": [],
    "stateMutability": "nonpayable",
    "type": "function"
  },
  {
    "inputs": [],
    "name": "owner",
    "outputs": [
      {
        "internalType": "address",
        "name": "",
        "type": "address"
      }
    ],
    "stateMutability": "view",
    "type": "function"
  },
  {
    "inputs": [
      {
        "components": [
          {
            "internalType": "address",
            "name": "from",
            "type": "address"
          },
          {
            "internalType": "address",
            "name": "to",
            "type": "address"
          },
          {
            "internalType": "address",
            "name": "withToken",
            "type": "address"
          }
        ],
        "internalType": "struct LoanFlow",
        "name": "fundFlow",
        "type": "tuple"
      },
      {
        "components": [
          {
            "internalType": "address",
            "name": "from",
            "type": "address"
          },
          {
            "internalType": "address",
            "name": "to",
            "type": "address"
          },
          {
            "internalType": "address",
            "name": "withToken",
            "type": "address"
          }
        ],
        "internalType": "struct LoanFlow",
        "name": "repayFlow",
        "type": "tuple"
      },
      {
        "components": [
          {
            "internalType": "uint256",
            "name": "loanAmount",
            "type": "uint256"
          },
          {
            "internalType": "uint256",
            "name": "interestRate",
            "type": "uint256"
          },
          {
            "internalType": "uint256",
            "name": "expectedRepaymentAmount",
            "type": "uint256"
          },
          {
            "internalType": "uint256",
            "name": "deadlineBlockNumber",
            "type": "uint256"
          }
        ],
        "internalType": "struct LoanTerms",
        "name": "loanTerms",
        "type": "tuple"
      },
      {
        "internalType": "bytes",
        "name": "signatureOfLender",
        "type": "bytes"
      },
      {
        "internalType": "bytes",
        "name": "signatureOfBorrower",
        "type": "bytes"
      }
    ],
    "name": "registerLoan",
    "outputs": [
      {
        "internalType": "uint256",
        "name": "",
        "type": "uint256"
      }
    ],
    "stateMutability": "nonpayable",
    "type": "function"
  },
  {
    "inputs": [
      {
        "internalType": "uint256",
        "name": "",
        "type": "uint256"
      }
    ],
    "name": "registeredLoans",
    "outputs": [
      {
        "internalType": "bool",
        "name": "",
        "type": "bool"
      }
    ],
    "stateMutability": "view",
    "type": "function"
  },
  {
    "inputs": [],
    "name": "renounceOwnership",
    "outputs": [],
    "stateMutability": "nonpayable",
    "type": "function"
  },
  {
    "inputs": [
      {
        "internalType": "address",
        "name": "newOwner",
        "type": "address"
      }
    ],
    "name": "transferOwnership",
    "outputs": [],
    "stateMutability": "nonpayable",
    "type": "function"
  }
]
